pgraphdb/__init__.py
pgraphdb/py.typed
pgraphdb/ui.py
pgraphdb/util.py
pgraphdb/version.py
pgraphdb-1.0.1.dist-info/METADATA
pgraphdb-1.0.1.dist-info/WHEEL
pgraphdb-1.0.1.dist-info/entry_points.txt
pgraphdb-1.0.1.dist-info/top_level.txt
pgraphdb-1.0.1.dist-info/RECORD
